python_projector/__init__.py
python_projector/cli/__init__.py
python_projector/cli/api.py
python_projector/cli/main.py
python_projector/scripts/pip_compile.sh
python_projector/scripts/run_doctest.py
python_projector/utils/__init__.py
python_projector/utils/deferred_logger.py
python_projector/utils/files.py
python_projector/utils/toml.py
python_projector/utils/version.py
python_projector/_version.py
python_projector-0.1.9.dist-info/METADATA
python_projector-0.1.9.dist-info/WHEEL
python_projector-0.1.9.dist-info/entry_points.txt
python_projector-0.1.9.dist-info/licenses/LICENSE
python_projector-0.1.9.dist-info/RECORD
