Metadata-Version: 2.4
Name: python-projector
Version: 0.1.9
Summary: Python project template
Project-URL: Homepage, https://github.com/deargen/workflows
Author: Kiyoon Kim
License:                                  Apache License
License-File: LICENSE
Keywords: development,template
Classifier: License :: OSI Approved :: Apache Software License
Classifier: Programming Language :: Python
Classifier: Programming Language :: Python :: 3
Classifier: Programming Language :: Python :: 3.11
Classifier: Programming Language :: Python :: 3.12
Classifier: Programming Language :: Python :: 3.13
Classifier: Programming Language :: Python :: Implementation :: CPython
Requires-Python: <4,>=3.11
Requires-Dist: packaging
Requires-Dist: platformdirs
Requires-Dist: rich>=13.0.0
Requires-Dist: tqdm>=4.0.0
Requires-Dist: typer>=0.12.4
Requires-Dist: versioneer>=0.29
Provides-Extra: dev
Requires-Dist: pytest-cov>=4.1.0; extra == 'dev'
Requires-Dist: pytest>=8.0.1; extra == 'dev'
Requires-Dist: ruff==0.8.0; extra == 'dev'
Requires-Dist: types-seaborn; extra == 'dev'
Requires-Dist: types-tqdm==4.66.0.20240106; extra == 'dev'
Requires-Dist: version-pioneer; extra == 'dev'
